quantix/__init__.py
quantix/core/__init__.py
quantix/core/backtest.py
quantix/core/signals.py
quantix/core/strategy.py
quantix/data/__init__.py
quantix/data/loader.py
quantix/indicators/__init__.py
quantix_trading-0.2.0.dist-info/LICENSE
quantix_trading-0.2.0.dist-info/METADATA
quantix_trading-0.2.0.dist-info/WHEEL
quantix_trading-0.2.0.dist-info/RECORD
