Metadata-Version: 2.3
Name: quantix-trading
Version: 0.2.0
Summary: Fast and intuitive backtesting for Python
License: MIT
Keywords: backtesting,trading,finance,quantitative,quant,algorithmic-trading
Author: Ivan Sharapenkov
Author-email: ivan.sharapenkov@assaia.com
Requires-Python: >=3.10
Classifier: Development Status :: 2 - Pre-Alpha
Classifier: Intended Audience :: Financial and Insurance Industry
Classifier: Intended Audience :: Science/Research
Classifier: License :: OSI Approved :: MIT License
Classifier: Programming Language :: Python :: 3
Classifier: Programming Language :: Python :: 3.10
Classifier: Programming Language :: Python :: 3.11
Classifier: Programming Language :: Python :: 3.12
Classifier: Programming Language :: Python :: 3.13
Classifier: Topic :: Office/Business :: Financial :: Investment
Classifier: Topic :: Scientific/Engineering :: Information Analysis
Classifier: Operating System :: OS Independent
Requires-Dist: numba (>=0.61.2,<0.62.0)
Requires-Dist: numpy (>=2.2.6,<3.0.0)
Requires-Dist: pandas (>=2.2.3,<3.0.0)
Project-URL: Documentation, https://github.com/quantix-io/quantix
Project-URL: Homepage, https://github.com/quantix-io/quantix
Project-URL: Issues, https://github.com/quantix-io/quantix/issues
Project-URL: Repository, https://github.com/quantix-io/quantix
